AUTHORS.txt
CHANGES.rst
CLASSIFIERS.txt
MANIFEST.in
README.rst
REQUIREMENTS.txt
setup.py
test/test_task.py
test/test_tasks.py
test/test_util.py
todotxt/__init__.py
todotxt/__init__.pyc
todotxt/cli.py
todotxt/task.py
todotxt/task.pyc
todotxt/util.py
todotxt/util.pyc
todotxt/__pycache__/__init__.cpython-36.pyc
todotxt/__pycache__/cli.cpython-36.pyc
todotxt/__pycache__/task.cpython-36.pyc
todotxt/__pycache__/util.cpython-36.pyc
todotxt_cli.egg-info/PKG-INFO
todotxt_cli.egg-info/SOURCES.txt
todotxt_cli.egg-info/dependency_links.txt
todotxt_cli.egg-info/entry_points.txt
todotxt_cli.egg-info/not-zip-safe
todotxt_cli.egg-info/requires.txt
todotxt_cli.egg-info/top_level.txt