Metadata-Version: 1.1
Name: todotxt-cli
Version: 0.3.1
Summary: manage todolist of todotxt
Home-page: https://github.com/fraoustin/todotxt-cli.git
Author: Frederic Aoustin
Author-email: fraoustin@gmail.com
License: UNKNOWN
Platform: any
Classifier: Programming Language :: Python
Classifier: License :: OSI Approved :: GNU General Public License v2 (GPLv2)
Classifier: Operating System :: OS Independent
Classifier: Programming Language :: Python :: 2.7
Classifier: Programming Language :: Python :: 3
Classifier: Programming Language :: Python :: 3.0
Classifier: Programming Language :: Python :: 3.1
Classifier: Programming Language :: Python :: 3.2
Classifier: Programming Language :: Python :: 3.3
Classifier: Programming Language :: Python :: 3.4
Classifier: Programming Language :: Python :: 3.5
Classifier: Programming Language :: Python :: 3.6
Classifier: Topic :: Software Development :: Libraries :: Python Modules
